debuglens/__init__.py
debuglens/__main__.py
debuglens/lens.py
debuglens-0.1.0.dist-info/licenses/LICENSE
debuglens-0.1.0.dist-info/METADATA
debuglens-0.1.0.dist-info/WHEEL
debuglens-0.1.0.dist-info/top_level.txt
debuglens-0.1.0.dist-info/RECORD
